skapp/__init__.py
skapp/cli.py
skapp/extensions/__init__.py
skapp/extensions/rabbitmq.py
skapp/models/__init__.py
skapp/models/base.py
skapp/models/build.py
skapp/models/pod_controllers.py
skapp/models/resource.py
skapp/models/stack.py
skapp/thirdparty/__init__.py
skapp/thirdparty/cnpg/__init__.py
skapp/thirdparty/cnpg/cluster.py
skapp/utils.py
skapp-0.1.47.dist-info/LICENSE
skapp-0.1.47.dist-info/METADATA
skapp-0.1.47.dist-info/WHEEL
skapp-0.1.47.dist-info/entry_points.txt
skapp-0.1.47.dist-info/RECORD
