Metadata-Version: 2.1
Name: skapp
Version: 0.1.47
Summary: 
Author: Darwin Monroy
Author-email: contact@darwinmonroy.com
Requires-Python: >=3.8,<4.0
Classifier: Programming Language :: Python :: 3
Classifier: Programming Language :: Python :: 3.8
Classifier: Programming Language :: Python :: 3.9
Classifier: Programming Language :: Python :: 3.10
Classifier: Programming Language :: Python :: 3.11
Requires-Dist: Jinja2 (>=3.1.1,<4.0.0)
Requires-Dist: PyYAML (>=6.0,<7.0)
Requires-Dist: docker (>=6.1.3,<7.0.0)
Requires-Dist: dockerfile-parse (>=2.0.1,<3.0.0)
Requires-Dist: kubernetes (<30)
Requires-Dist: parameterize (>=0.2,<0.3)
Requires-Dist: pydantic (>=1.9.0,<2.0.0)
Requires-Dist: python-dotenv (>=1.0.1,<2.0.0)
Requires-Dist: python-on-whales (>=0.65.0,<0.66.0)
Requires-Dist: requests (<2.32)
Requires-Dist: rich (>=13.9.4,<14.0.0)
Requires-Dist: typer (>=0.4.1,<0.5.0)
